skerch/__init__.py
skerch/__main__.py
skerch/a_posteriori.py
skerch/algorithms.py
skerch/hdf5.py
skerch/linops.py
skerch/measurements.py
skerch/recovery.py
skerch/synthmat.py
skerch/utils.py
skerch/cli/__init__.py
skerch/cli/create_hdf5_layout_lop.py
skerch/cli/merge_hdf5.py
skerch/cli/post_bounds.py
skerch-1.2.0.dist-info/licenses/LICENSE
test/__init__.py
test/conftest.py
test/test_a_posteriori.py
test/test_algorithms.py
test/test_cli.py
test/test_hdf5.py
test/test_linop_aggregate.py
test/test_linop_base.py
test/test_linop_subtypes.py
test/test_linop_torchwrapper.py
test/test_measurements.py
test/test_recovery.py
test/test_synthmat.py
test/test_utils.py
skerch-1.2.0.dist-info/METADATA
skerch-1.2.0.dist-info/WHEEL
skerch-1.2.0.dist-info/top_level.txt
skerch-1.2.0.dist-info/RECORD
