Metadata-Version: 2.4
Name: skerch
Version: 1.2.0
Summary: Sketched matrix decompositions for PyTorch
Home-page: https://github.com/andres-fr/skerch
Author: aferro
License: MIT
Platform: any
Classifier: Development Status :: 4 - Beta
Classifier: License :: OSI Approved :: MIT License
Classifier: Operating System :: OS Independent
Classifier: Programming Language :: Python :: 3.10
Classifier: Programming Language :: Python :: 3.11
Classifier: Programming Language :: Python :: 3.12
Requires-Python: >=3.10
License-File: LICENSE
Requires-Dist: torch<3.0.0,>=2.1.0
Requires-Dist: scipy<2.0.0,>=1.10.0
Requires-Dist: h5py<4.0.0,>=3.9.0
Requires-Dist: torch-dct<2.0.0,>=0.1.6
Provides-Extra: dev
Requires-Dist: pre-commit; extra == "dev"
Requires-Dist: commitizen; extra == "dev"
Provides-Extra: test
Requires-Dist: coveralls; extra == "test"
Requires-Dist: pytest; extra == "test"
Requires-Dist: pytest-cov; extra == "test"
Provides-Extra: lint
Requires-Dist: black; extra == "lint"
Requires-Dist: flake8; extra == "lint"
Requires-Dist: mccabe; extra == "lint"
Requires-Dist: pep8-naming; extra == "lint"
Requires-Dist: flake8-bugbear; extra == "lint"
Requires-Dist: flake8-comprehensions; extra == "lint"
Requires-Dist: flake8-tidy-imports; extra == "lint"
Requires-Dist: darglint; extra == "lint"
Requires-Dist: pydocstyle; extra == "lint"
Requires-Dist: isort; extra == "lint"
Provides-Extra: docs
Requires-Dist: matplotlib; extra == "docs"
Requires-Dist: curvlinops-for-pytorch>=3; extra == "docs"
Requires-Dist: sphinx-gallery; extra == "docs"
Requires-Dist: sphinx-rtd-theme; extra == "docs"
Requires-Dist: sphinx-immaterial; extra == "docs"
Dynamic: license-file
